{
  "text": [
    {
      "text": "Sending Server Configuration",
      "color": "white"
    },
    {
      "text": "Sending Server **Configuration**",
      "variant": "h3"
    },
    {
      "text": "The ESP version of MumaraClassic has made the challenging task of configuring an email infrastructure fairly easy. The seamless integration of market leader Mail Transfer Agent PowerMTA™ with all its valuable directives would help you design an infrastructure capable for high performance email delivery.",
      "variant": "medium"
    }
  ],
  "images": [
    {
      "src": "../../assets/flexiblocks/classic-esp/server.jpg",
      "alt": "Sending Server",
      "radius": "lg",
      "shadow": "default"
    },
    {
      "src": "../../assets/flexiblocks/classic-esp/servers.png",
      "alt": "servers",
      "effects": ["fadeInDown", "float"],
      "position": {
        "bottom": "-15%",
        "left": "10%"
      }
    },
    {
      "src": "../../assets/flexiblocks/classic-esp/servers-config.jpg",
      "alt": "servers config",
      "radius": "lg",
      "shadow": "default",
      "effects": ["fadeInUp", "floatFaster"],
      "position": {
        "top": "-10%",
        "right": "0%"
      }
    }
  ],
  "buttons": [
    {
      "text": "Learn more   ➜",
      "type": "PAGE",
      "link": "/classic-esp/sending-server-configuration/",
      "variant": "links.normal"
    }
  ]
}
