{
  "text": [
    {
      "text": "Client Management",
      "color": "white"
    },
    {
      "text": "**Client** Management",
      "variant": "h3"
    },
    {
      "text": "Add as many client accounts as you require and assign them a client group as per the package they have subscribed. The “Client Group” function offers access control list to control the access level of the client accounts, and resource restriction capability to limit the use of resources and sending volume according to the different client packages.",
      "variant": "medium"
    }
  ],
  "images": [
    {
      "src": "../../assets/flexiblocks/classic-esp/user-main.jpg",
      "alt": "Client Management",
      "radius": "lg",
      "shadow": "default"
    },
    {
      "src": "../../assets/flexiblocks/classic-esp/user.png",
      "alt": "User",
      "radius": "lg",
      "shadow": "default",
      "effects": ["fadeInDown", "float"],
      "position": {
        "bottom": "15%",
        "left": "25%"
      }
    }
  ],
  "buttons": [
    {
      "text": "Learn more   ➜",
      "type": "PAGE",
      "link": "/classic-esp/client-management/",
      "variant": "links.normal"
    }
  ]
}
