{
  "text": [
    {
      "text": "Restrict access to only **trusted IP addresses**",
      "variant": "h2"
    },
    {
      "text": "Restrict Mumara’s account accessibility to specific IP addresses or a block of IP addresses. Once permitted, only permitted IP addresses will be able to sign in.",
      "variant": "medium"
    }
  ],
  "images": [
    {
      "src": "../../../../assets/flexiblocks/campaigns/features/profile-timezone.png",
      "radius": "lg",
      "alt": "Flexible",
      "effects": ["fadeInLeft", "float"]
    }
  ]
}
