{
  "text": [
    {
      "text": "**General** Identifiable Data:",
      "color": "omegaDarker",
      "variant": "h4"
    },
    {
      "text": "As long as you are browsing our website for collecting information, we don’t record any information except non personal information (IP address, Browser Type, Geographical Location etc) recorded by software like Google Analytics for traffic analysis on the website. However, when you go further from just browsing and reading about the products/services we offer, we do collect personal information to process various requested services. The personal information is required if you are looking to take a tour to the demo of the products that we offer, if you subscribe to our newsletters or go for a purchase.",
      "color": "omegaDark",
      "variant": "medium"
    },
    {
      "text": "The personal information that we collect includes email address, name, mobile number, address, postal code and such.  The fields of the registration form indicate the mandatory information which is required to sing-up for an account with Mumara. Filling the sign-up form indicates your consent to share this necessary information with us, this information is primarily used to provision the requested services and will later be used by Mumara for future correspondence, assistance, and support.",
      "color": "omegaDark",
      "variant": "medium"
    }
    ,
    {
      "text": "Other information you volunteer for any electronic submission.",
      "color": "omegaDark",
      "variant": "medium"
    }
  ]
}
