{
  "text": [
    {
      "text": "User **Accounts**",
      "variant": "h2"
    },
    {
      "text": "Add users to let them send emails for themselves. The users are responsible for their own data/assets that are not shareable with other users.",
      "variant": "medium"
    }
  ],
  "images": [
    {
      "src": "../../assets/flexiblocks/campaigns/add-user.jpg",
      "radius": "lg",
      "alt": "User Accounts",
      "effects": ["fadeInLeft", "float"]
    }
  ],
  "buttons": [
    {
      "text": "Learn More",
      "type": "PAGE",
      "link": "/campaigns/features/user-management/#user-accounts",
      "variant": "primary-light"
    }
  ]
}
